etool/__init__.py
etool/_md/__init__.py
etool/_md/_md_to_docx.py
etool/_network/__init__.py
etool/_network/_share.py
etool/_network/_speed.py
etool/_office/__init__.py
etool/_office/_docx.py
etool/_office/_email.py
etool/_office/_excel.py
etool/_office/_image.py
etool/_office/_ipynb.py
etool/_office/_pdf.py
etool/_office/_qrcode.py
etool/_other/__init__.py
etool/_other/_install.py
etool/_other/_menu.py
etool/_other/_password.py
etool/_other/_scheduler.py
etool-1.4.5.dist-info/licenses/LICENSE
etool-1.4.5.dist-info/METADATA
etool-1.4.5.dist-info/WHEEL
etool-1.4.5.dist-info/top_level.txt
etool-1.4.5.dist-info/RECORD
