Metadata-Version: 2.4
Name: etool
Version: 1.4.5
Summary: A etool package for security monitoring
Author-email: Allen <jiangyangcreate@gmail.com>
Project-URL: Homepage, https://github.com/jiangyangcreate/etool
Project-URL: Issues, https://github.com/jiangyangcreate/etool/issues
Classifier: Programming Language :: Python :: 3
Classifier: License :: OSI Approved :: Apache Software License
Classifier: Operating System :: OS Independent
Requires-Python: >=3.6
License-File: LICENSE
Requires-Dist: schedule>=1.1.0
Requires-Dist: speedtest-cli
Requires-Dist: flask
Requires-Dist: pillow
Requires-Dist: pypdf
Requires-Dist: openpyxl
Requires-Dist: numpy
Requires-Dist: numba
Requires-Dist: opencv-python-headless
Requires-Dist: python-docx
Requires-Dist: easyqr
Requires-Dist: MyQR
Requires-Dist: qrcode
Requires-Dist: scikit-image
Requires-Dist: pdf2docx
Requires-Dist: markdown
Requires-Dist: beautifulsoup4
Dynamic: license-file
